finfo/FIE.py
finfo/PDF_reader.py
finfo/PDF_replacer.py
finfo/__init__.py
finfo/exceptions.py
tests/__init__.py
tests/test_fie.py
finfo-3.dist-info/LICENSE.txt
finfo-3.dist-info/METADATA
finfo-3.dist-info/WHEEL
finfo-3.dist-info/top_level.txt
finfo-3.dist-info/RECORD
