Metadata-Version: 2.1
Name: finfo
Version: 3
Summary: Package used to find fencers ranking placements.
Home-page: https://gitlab.com/hann1ba1/finfo
Author: Hannibal Lykke Kofoed
Author-email: hanniballykkekofoed@icloud.com
License: MIT
Keywords: python,fencing,rankings
Classifier: License :: OSI Approved :: MIT License
Classifier: Programming Language :: Python :: 3
Classifier: Operating System :: OS Independent
License-File: LICENSE.txt
Requires-Dist: pypdf
Requires-Dist: requests
